conspiracies/__init__.py
conspiracies/about.py
conspiracies/document.py
conspiracies/registry.py
conspiracies/run.py
conspiracies/common/__init__.py
conspiracies/common/fileutils.py
conspiracies/common/modelchoice.py
conspiracies/corpusprocessing/__init__.py
conspiracies/corpusprocessing/umap_hdb.py
conspiracies/docprocessing/__init__.py
conspiracies/docprocessing/doc_utils.py
conspiracies/docprocessing/docprocessor.py
conspiracies/docprocessing/modeldownload.py
conspiracies/docprocessing/coref/__init__.py
conspiracies/docprocessing/coref/coref_component.py
conspiracies/docprocessing/coref/coref_model.py
conspiracies/docprocessing/headwordextraction/__init__.py
conspiracies/docprocessing/headwordextraction/headwordextraction_component.py
conspiracies/docprocessing/relationextraction/__init__.py
conspiracies/docprocessing/relationextraction/data_classes.py
conspiracies/docprocessing/relationextraction/gptprompting/__init__.py
conspiracies/docprocessing/relationextraction/gptprompting/prompt_apis.py
conspiracies/docprocessing/relationextraction/gptprompting/prompt_relation_component.py
conspiracies/docprocessing/relationextraction/gptprompting/prompt_templates.py
conspiracies/docprocessing/relationextraction/gptprompting/prompt_utils.py
conspiracies/docprocessing/relationextraction/multi2oie/__init__.py
conspiracies/docprocessing/relationextraction/multi2oie/dataset.py
conspiracies/docprocessing/relationextraction/multi2oie/extract.py
conspiracies/docprocessing/relationextraction/multi2oie/knowledge_triplets.py
conspiracies/docprocessing/relationextraction/multi2oie/model.py
conspiracies/docprocessing/relationextraction/multi2oie/multi2oie_component.py
conspiracies/docprocessing/relationextraction/multi2oie/multi2oie_utils.py
conspiracies/docprocessing/relationextraction/multi2oie/other/__init__.py
conspiracies/docprocessing/relationextraction/multi2oie/other/bio.py
conspiracies/docprocessing/relationextraction/multi2oie/other/utils.py
conspiracies-0.8.0.dist-info/LICENSE
conspiracies-0.8.0.dist-info/METADATA
conspiracies-0.8.0.dist-info/WHEEL
conspiracies-0.8.0.dist-info/entry_points.txt
conspiracies-0.8.0.dist-info/top_level.txt
conspiracies-0.8.0.dist-info/RECORD
