Metadata-Version: 2.1
Name: conspiracies
Version: 0.8.0
Summary: Discover and examine conspiracies using natural language processing
Author: "Kenneth Enevoldsen, Lasse Hansen, Ekaterina Borisova, Stephan Smuts"
License: MIT License
Project-URL: homepage, https://github.com/centre-for-humanities-computing/conspiracies
Project-URL: repository, https://github.com/centre-for-humanities-computing/conspiracies
Project-URL: documentation, https://centre-for-humanities-computing.github.io/conspiracies/
Classifier: Intended Audience :: Developers
Classifier: Intended Audience :: Science/Research
Classifier: Topic :: Scientific/Engineering
Classifier: Topic :: Scientific/Engineering :: Artificial Intelligence
Classifier: Operating System :: POSIX :: Linux
Classifier: Operating System :: MacOS :: MacOS X
Classifier: Programming Language :: Python :: 3
Classifier: Programming Language :: Python :: 3.7
Classifier: Programming Language :: Python :: 3.8
Classifier: Programming Language :: Python :: 3.9
Classifier: License :: OSI Approved :: MIT License
Requires-Python: >=3.8
License-File: LICENSE
Requires-Dist: spacy <3.6.0,>=3.3.2
Requires-Dist: spacy-transformers <1.2.0,>=1.1.2
Requires-Dist: confection <0.1.0,>0.0.1
Requires-Dist: allennlp <2.11.0,>=2.10.0
Requires-Dist: allennlp-models <2.11.0,>=2.10.0
Requires-Dist: transformers <4.19.0,>=4.11.3
Requires-Dist: torch <1.12.0,>=1.6.0
Requires-Dist: numpy <1.24.0,>=1.19.5
Requires-Dist: pandas <1.5.0,>=1.1.5
Requires-Dist: jsonlines <3.2.0,>=3.1.0
Requires-Dist: openai
Requires-Dist: ndjson
Requires-Dist: networkx
Requires-Dist: matplotlib
Requires-Dist: umap-learn
Requires-Dist: hdbscan
Requires-Dist: sentence-transformers
Requires-Dist: stop-words
Requires-Dist: bs4
Requires-Dist: toml
Provides-Extra: docs
Requires-Dist: sphinx <5.4.0,>=5.3.0 ; extra == 'docs'
Requires-Dist: furo ==2022.12.7 ; extra == 'docs'
Requires-Dist: sphinx-copybutton <0.5.2,>=0.5.1 ; extra == 'docs'
Requires-Dist: sphinxext-opengraph <0.7.4,>=0.7.3 ; extra == 'docs'
Requires-Dist: sphinx-design <0.3.1,>=0.3.0 ; extra == 'docs'
Requires-Dist: myst-nb <1.17.0,>=0.6.0 ; extra == 'docs'
Requires-Dist: sphinx-togglebutton <0.4.0,>=0.2.3 ; extra == 'docs'
Provides-Extra: openai
Requires-Dist: openai <0.27.0,>=0.26.5 ; extra == 'openai'
Provides-Extra: style
Requires-Dist: black ==22.12.0 ; extra == 'style'
Requires-Dist: pre-commit <2.21.0,>=2.20.0 ; extra == 'style'
Requires-Dist: ruff ==0.0.191 ; extra == 'style'
Requires-Dist: mypy ==0.991 ; extra == 'style'
Provides-Extra: tests
Requires-Dist: pytest <7.3.0,>=7.1.3 ; extra == 'tests'
Requires-Dist: pytest-cov <3.1.0,>=3.0.0 ; extra == 'tests'
Provides-Extra: tutorials
Requires-Dist: jupyter <1.1.0,>=1.0.0 ; extra == 'tutorials'
